lct/main_window.py
lct/version.py
lct/__init__.py
lct/db/moon.db
lct/features/lunar_feature.py
lct/features/lunar_feature_container.py
lct/features/__init__.py
lct/images/exit.svg
lct/images/location.svg
lct/images/moon_large.svg
lct/images/star-off.svg
lct/images/star-on.svg
lct/ui/mainwindow.ui
lct/ui/main_resources_rc.py
lct/ui/ui_mainwindow.py
lct/ui/__init__.py
lct/ui/widgets/fraction_widget.py
lct/ui/widgets/location_config.py
lct/ui/widgets/location_config.ui
lct/ui/widgets/lunar_club_special_widget.py
lct/ui/widgets/lunar_club_special_widget.ui
lct/ui/widgets/lunar_club_tab.py
lct/ui/widgets/lunar_club_tab.ui
lct/ui/widgets/lunar_two_tab.py
lct/ui/widgets/lunar_two_tab.ui
lct/ui/widgets/moon_info_tab.py
lct/ui/widgets/moon_info_tab.ui
lct/ui/widgets/ui_location_config.py
lct/ui/widgets/ui_lunar_club_special_widget.py
lct/ui/widgets/ui_lunar_club_tab.py
lct/ui/widgets/ui_lunar_two_tab.py
lct/ui/widgets/ui_moon_info_tab.py
lct/ui/widgets/widget_resources_rc.py
lct/ui/widgets/__init__.py
lct/utils/constants.py
lct/utils/converter.py
lct/utils/moon_info.py
lct/utils/observing_info.py
lct/utils/observing_site.py
lct/utils/string_format.py
lct/utils/__init__.py
lct-0.4.0.data/scripts/lunar_club_tools.py
lct-0.4.0.dist-info/DESCRIPTION.rst
lct-0.4.0.dist-info/METADATA
lct-0.4.0.dist-info/metadata.json
lct-0.4.0.dist-info/RECORD
lct-0.4.0.dist-info/top_level.txt
lct-0.4.0.dist-info/WHEEL
