Metadata-Version: 2.0
Name: lct
Version: 0.4.0
Summary: Lunar Club Tools
Home-page: https://github.com/mareuter/lct-python
Author: Michael Reuter
Author-email: mareuternh@gmail.com
License: MIT
Platform: Linux
Platform: OSX
Platform: Windows
Classifier: Programming Language :: Python
Classifier: Programming Language :: Python :: 2
Classifier: License :: OSI Approved :: MIT License
Classifier: Operating System :: OS Independent
Classifier: Development Status :: 3 - Alpha
Classifier: Intended Audience :: Science/Research
Classifier: Intended Audience :: End Users/Desktop
Classifier: Topic :: Scientific/Engineering :: Astronomy
Requires-Dist: pyephem
Requires-Dist: qdarkstyle
Requires-Dist: tzlocal
